topsis/__init__.py
topsis/topsis.py
102217106_topsis-1.0.0.dist-info/METADATA
102217106_topsis-1.0.0.dist-info/WHEEL
102217106_topsis-1.0.0.dist-info/top_level.txt
102217106_topsis-1.0.0.dist-info/RECORD
