Metadata-Version: 2.1
Name: 102217106_topsis
Version: 1.0.0
Summary: A simple TOPSIS implementation package.
Author: Deepansh Patni
Author-email: deepanshpatni@gmail.com
Classifier: Programming Language :: Python :: 3
Classifier: License :: OSI Approved :: MIT License
Classifier: Operating System :: OS Independent
Requires-Python: >=3.6
Requires-Dist: numpy
